kt3extract/__init__.py
kt3extract/__main__.py
kt3extract/kt3extract.py
kt3extract-0.0.1.dist-info/METADATA
kt3extract-0.0.1.dist-info/WHEEL
kt3extract-0.0.1.dist-info/entry_points.txt
kt3extract-0.0.1.dist-info/top_level.txt
kt3extract-0.0.1.dist-info/RECORD
