Metadata-Version: 2.4
Name: kt3extract
Version: 0.0.1
Summary: Kill Team 3rd edition datacard extractor
Home-page: https://github.com/chrismettal/Kill-Team-datacard-extractor
Author: Chrismettal
Author-email: Chrismettal <chrismettal@binary-6.de>
Maintainer-email: Chrismettal <chrismettal@binary-6.de>
License-Expression: GPL-3.0-or-later
Requires-Python: >=3.13
Requires-Dist: pypdf
